docs/adb_cli.png
docs/adb_pure_python_adb.png
example/screencap.py
ppadb/__init__.py
ppadb/application.py
ppadb/client.py
ppadb/client_async.py
ppadb/connection.py
ppadb/connection_async.py
ppadb/device.py
ppadb/device_async.py
ppadb/keycode.py
ppadb/protocol.py
ppadb/command/__init__.py
ppadb/command/host/__init__.py
ppadb/command/host_async/__init__.py
ppadb/command/serial/__init__.py
ppadb/command/transport/__init__.py
ppadb/command/transport_async/__init__.py
ppadb/plugins/__init__.py
ppadb/plugins/client/__init__.py
ppadb/plugins/device/__init__.py
ppadb/plugins/device/batterystats.py
ppadb/plugins/device/batterystats_section.py
ppadb/plugins/device/cpustat.py
ppadb/plugins/device/input.py
ppadb/plugins/device/traffic.py
ppadb/plugins/device/utils.py
ppadb/plugins/device/wm.py
ppadb/sync/__init__.py
ppadb/sync/stats.py
ppadb/sync_async/__init__.py
ppadb/utils/__init__.py
ppadb/utils/logger.py
scripts/batterystats_codegen.py
test_async/__init__.py
test_async/async_wrapper.py
test_async/patchers.py
test_async/test_client_async.py
test_async/test_connection_async.py
test_async/test_device_async.py
pure_python_adb_reborn-1.0.0.dist-info/LICENSE
pure_python_adb_reborn-1.0.0.dist-info/METADATA
pure_python_adb_reborn-1.0.0.dist-info/WHEEL
pure_python_adb_reborn-1.0.0.dist-info/top_level.txt
pure_python_adb_reborn-1.0.0.dist-info/RECORD
