Metadata-Version: 2.2
Name: pure-python-adb-reborn
Version: 1.0.0
Summary: Pure python implementation of the adb client.
Maintainer: Sergio Martins, Andrew Butcher
License: MIT
Project-URL: Repository, https://github.com/spm5065/pure-python-adb.git
Project-URL: Issues, https://github.com/spm5065/pure-python-adb/issues
Project-URL: Changelog, https://github.com/spm5065/pure-python-adb/blob/master/HISTORY.rst
Keywords: adb,android,async
Classifier: Development Status :: 5 - Production/Stable
Classifier: Intended Audience :: Developers
Classifier: License :: OSI Approved :: MIT License
Classifier: Programming Language :: Python :: 3
Classifier: Topic :: Software Development :: Testing
Requires-Python: >=3.12
License-File: LICENSE
Requires-Dist: Exscript
Requires-Dist: aiofiles>=0.4.0
Requires-Dist: pytest[dev]
Requires-Dist: black[dev]
Requires-Dist: ruff[dev]
